arpest/__init__.py
arpest/app.py
arpest/core/__init__.py
arpest/core/loaders/__init__.py
arpest/core/loaders/base.py
arpest/core/loaders/bloch.py
arpest/core/loaders/i05.py
arpest/models/__init__.py
arpest/models/dataset.py
arpest/models/file_stack.py
arpest/operations/__init__.py
arpest/operations/background.py
arpest/operations/basic.py
arpest/operations/curvature.py
arpest/operations/export.py
arpest/operations/fermi.py
arpest/operations/fit.py
arpest/operations/k_space.py
arpest/operations/normalise_slices.py
arpest/operations/rotate.py
arpest/ui/__init__.py
arpest/ui/dataset_tab.py
arpest/ui/main_window.py
arpest/ui/dialogs/__init__.py
arpest/ui/dialogs/settings.py
arpest/ui/panels/__init__.py
arpest/ui/panels/analysis/__init__.py
arpest/ui/panels/analysis/history.py
arpest/ui/panels/analysis/panel.py
arpest/ui/panels/analysis/widgets/__init__.py
arpest/ui/panels/analysis/widgets/base.py
arpest/ui/panels/analysis/widgets/fitting.py
arpest/ui/panels/analysis/widgets/overplot.py
arpest/ui/panels/analysis/widgets/registry.py
arpest/ui/panels/operations/__init__.py
arpest/ui/panels/operations/panel.py
arpest/ui/panels/operations/widgets/__init__.py
arpest/ui/panels/operations/widgets/state_history.py
arpest/ui/panels/operations/widgets/operations/__init__.py
arpest/ui/panels/operations/widgets/operations/background.py
arpest/ui/panels/operations/widgets/operations/base.py
arpest/ui/panels/operations/widgets/operations/basic.py
arpest/ui/panels/operations/widgets/operations/curvature.py
arpest/ui/panels/operations/widgets/operations/export.py
arpest/ui/panels/operations/widgets/operations/fermi_level.py
arpest/ui/panels/operations/widgets/operations/k_space.py
arpest/ui/panels/operations/widgets/operations/normalise_slices.py
arpest/ui/panels/operations/widgets/operations/registry.py
arpest/ui/panels/operations/widgets/operations/rotate.py
arpest/ui/panels/overview/__init__.py
arpest/ui/panels/overview/panel.py
arpest/ui/panels/overview/widgets/__init__.py
arpest-1.0.3.dist-info/LICENSE
arpest-1.0.3.dist-info/METADATA
arpest-1.0.3.dist-info/WHEEL
arpest-1.0.3.dist-info/entry_points.txt
arpest-1.0.3.dist-info/top_level.txt
arpest-1.0.3.dist-info/RECORD
