Metadata-Version: 2.1
Name: arpest
Version: 1.0.3
Summary: ARPES data analysis and visualization tool
Author: Ola Kenjiforslund
License: MIT
Requires-Python: >=3.7.13
License-File: LICENSE
Requires-Dist: numpy >=1.21.6
Requires-Dist: matplotlib >=3.5.3
Requires-Dist: scipy >=1.7.3
Requires-Dist: h5py >=3.6.0
Requires-Dist: pyqtgraph >=0.12.1
Requires-Dist: PyQt5 >=5.15.6
Requires-Dist: igor >=0.3
Provides-Extra: dev
Requires-Dist: pytest >=7.4.0 ; extra == 'dev'
Requires-Dist: pytest-qt >=4.2.0 ; extra == 'dev'
Requires-Dist: black >=23.0.0 ; extra == 'dev'
Requires-Dist: mypy >=1.5.0 ; extra == 'dev'
Requires-Dist: ruff >=0.0.290 ; extra == 'dev'
